hmrf.py
hmrf-0.2.0.dist-info/LICENSE.txt
hmrf-0.2.0.dist-info/METADATA
hmrf-0.2.0.dist-info/WHEEL
hmrf-0.2.0.dist-info/top_level.txt
hmrf-0.2.0.dist-info/RECORD
