Metadata-Version: 2.1
Name: hmrf
Version: 0.2.0
Summary: Package to extract keywords in one of the classes of a dataset
Home-page: UNKNOWN
Author: UPV
License: UNKNOWN
Platform: UNKNOWN
Classifier: Programming Language :: Python :: 3
Classifier: License :: OSI Approved :: MIT License
Classifier: Operating System :: OS Independent
Requires-Python: >=3.6
License-File: LICENSE.txt
Requires-Dist: iso639-lang
Requires-Dist: numpy
Requires-Dist: scikit-learn
Requires-Dist: pandas
Requires-Dist: nltk
Requires-Dist: scipy
